copernicusapi/__init__.py
copernicusapi/src/__init__.py
copernicusapi/src/_constants.py
copernicusapi/src/query.py
copernicusapi/src/query_constructor.py
copernicusapi/src/response.py
copernicusapi/src/vector.py
copernicusapi/tests/__init__.py
copernicusapi/tests/query_constructor_test.py
copernicusapi/tests/query_test.py
copernicusapi-0.1.3.dist-info/LICENSE
copernicusapi-0.1.3.dist-info/METADATA
copernicusapi-0.1.3.dist-info/WHEEL
copernicusapi-0.1.3.dist-info/top_level.txt
copernicusapi-0.1.3.dist-info/RECORD
