Metadata-Version: 2.1
Name: copernicusapi
Version: 0.1.3
Summary: A package to facilitate interactive construction of queries to the Copernicus Data Space Ecosystem repository.
Home-page: https://github.com/panopterra/copernicus-api
Author: Panopterra UG
Author-email: contact@panopterra.com
License: Apache 2.0
Keywords: copernicus,data space,esa,satellite,download,remote sensing,earth observation
Classifier: License :: OSI Approved :: Apache Software License
Classifier: Programming Language :: Python :: 3
Classifier: Operating System :: OS Independent
Classifier: Intended Audience :: Developers
Classifier: Intended Audience :: Science/Research
Classifier: Natural Language :: English
Classifier: Topic :: Scientific/Engineering :: GIS
Classifier: Topic :: Utilities
Requires-Python: >=3.10
License-File: LICENSE
Requires-Dist: geopandas>=0.14
Requires-Dist: numpy>=1.26
Requires-Dist: pandas>=2.0
Requires-Dist: pyproj>=3.6
Requires-Dist: shapely>=2.0
Provides-Extra: dev
Requires-Dist: black>=24.0; extra == "dev"
Requires-Dist: flake>=7.0; extra == "dev"
Requires-Dist: pytest-cov>=4.1; extra == "dev"
Requires-Dist: twine>=5.1; extra == "dev"
Requires-Dist: pytest>=8.0; extra == "dev"
